arsenal_2122/__init__.py
arsenal_2122/arsenal.py
arsenal_2122-0.1.dist-info/METADATA
arsenal_2122-0.1.dist-info/WHEEL
arsenal_2122-0.1.dist-info/top_level.txt
arsenal_2122-0.1.dist-info/RECORD
