Metadata-Version: 2.1
Name: arsenal-2122
Version: 0.1
Summary: UNKNOWN
Home-page: UNKNOWN
License: UNKNOWN
Platform: UNKNOWN
